package android.microntek.canbus.c;

class k
  implements Runnable
{
  k(j paramj, byte[] paramArrayOfByte)
  {
  }

  // ERROR //
  public void run()
  {
    // Byte code:
    //   0: aload_0
    //   1: getfield 14	android/microntek/canbus/c/k:dh	Landroid/microntek/canbus/c/j;
    //   4: invokestatic 28	android/microntek/canbus/c/j:a	(Landroid/microntek/canbus/c/j;)Z
    //   7: ifeq +40 -> 47
    //   10: aload_0
    //   11: getfield 14	android/microntek/canbus/c/k:dh	Landroid/microntek/canbus/c/j;
    //   14: invokestatic 28	android/microntek/canbus/c/j:a	(Landroid/microntek/canbus/c/j;)Z
    //   17: ifne +4 -> 21
    //   20: return
    //   21: ldc2_w 29
    //   24: invokestatic 36	java/lang/Thread:sleep	(J)V
    //   27: aload_0
    //   28: getfield 14	android/microntek/canbus/c/k:dh	Landroid/microntek/canbus/c/j;
    //   31: getfield 40	android/microntek/canbus/c/j:cv	Landroid/microntek/canbus/CanBusServer;
    //   34: bipush 32
    //   36: aload_0
    //   37: getfield 16	android/microntek/canbus/c/k:dg	[B
    //   40: iconst_2
    //   41: invokevirtual 45	android/microntek/canbus/CanBusServer:a	(B[BI)V
    //   44: goto -34 -> 10
    //   47: aload_0
    //   48: getfield 14	android/microntek/canbus/c/k:dh	Landroid/microntek/canbus/c/j;
    //   51: invokestatic 49	android/microntek/canbus/c/j:b	(Landroid/microntek/canbus/c/j;)Ljava/lang/Object;
    //   54: astore_1
    //   55: aload_1
    //   56: monitorenter
    //   57: iconst_0
    //   58: istore_2
    //   59: iload_2
    //   60: iconst_3
    //   61: if_icmpge +32 -> 93
    //   64: ldc2_w 29
    //   67: invokestatic 36	java/lang/Thread:sleep	(J)V
    //   70: aload_0
    //   71: getfield 14	android/microntek/canbus/c/k:dh	Landroid/microntek/canbus/c/j;
    //   74: getfield 40	android/microntek/canbus/c/j:cv	Landroid/microntek/canbus/CanBusServer;
    //   77: bipush 32
    //   79: aload_0
    //   80: getfield 16	android/microntek/canbus/c/k:dg	[B
    //   83: iconst_2
    //   84: invokevirtual 45	android/microntek/canbus/CanBusServer:a	(B[BI)V
    //   87: iinc 2 1
    //   90: goto -31 -> 59
    //   93: aload_1
    //   94: monitorexit
    //   95: goto -75 -> 20
    //   98: astore_3
    //   99: aload_1
    //   100: monitorexit
    //   101: aload_3
    //   102: athrow
    //   103: astore 5
    //   105: goto -78 -> 27
    //   108: astore 4
    //   110: goto -40 -> 70
    //
    // Exception table:
    //   from	to	target	type
    //   64	70	98	finally
    //   70	101	98	finally
    //   21	27	103	java/lang/Exception
    //   64	70	108	java/lang/Exception
  }
}

/* Location:           C:\Users\Ben\AppData\Local\Temp\MTCCanbus-dex2jar.jar
 * Qualified Name:     android.microntek.canbus.c.k
 * JD-Core Version:    0.6.2
 */